Metadata-Version: 1.1
Name: csvviewer
Version: 0.1.1
Summary: Command Line Delimited Text Viewer
Home-page: https://github.com/franklinsijo/csvviewer
Author: franklinsijo
Author-email: franklinsijo@gmail.com
License: MIT
Download-URL: https://github.com/franklinsijo/csvviewer/archive/refs/tags/0.1.0.tar.gz
Keywords: csv,command-line,reader
Platform: UNKNOWN
Classifier: Development Status :: 3 - Alpha
Classifier: Environment :: Console
Classifier: Intended Audience :: Developers
Classifier: Topic :: Software Development :: Build Tools
Classifier: License :: OSI Approved :: MIT License
Classifier: Natural Language :: English
Classifier: Operating System :: MacOS :: MacOS X
Classifier: Operating System :: POSIX
Classifier: Operating System :: POSIX :: Linux
Classifier: Programming Language :: Python :: 3
Classifier: Programming Language :: Python :: 3.4
Classifier: Programming Language :: Python :: 3.5
Classifier: Programming Language :: Python :: 3.6
Classifier: Programming Language :: Python :: 3.7
Classifier: Programming Language :: Python :: 3.8
Classifier: Programming Language :: Python :: 3.9
